setup.py
KnnLb/FileReader.py
KnnLb/KnnLb.py
KnnLb/__init__.py
apprunner/LbEnhanced.py
apprunner/README.md
apprunner/Runner.py
apprunner/Sequence_stats.py
datasets/.DS_Store
datasets/DirectoryNames.py
datasets/FreezerRegularTrain.zip
datasets/Plane.zip
datasets/arffToCsv.py
datasets/convertToCsv.sh
datasets/Chinatown/Chinatown.txt
datasets/Chinatown/Chinatown_TEST.arff
datasets/Chinatown/Chinatown_TEST.csv
datasets/Chinatown/Chinatown_TEST.ts
datasets/Chinatown/Chinatown_TEST.txt
datasets/Chinatown/Chinatown_TRAIN.arff
datasets/Chinatown/Chinatown_TRAIN.csv
datasets/Chinatown/Chinatown_TRAIN.ts
datasets/Chinatown/Chinatown_TRAIN.txt
datasets/Chinatown/README.md
datasets/ERing/ERing_TEST.arff
datasets/ERing/ERing_TRAIN.arff
datasets/FacesUCR/FacesUCR.txt
datasets/FacesUCR/FacesUCR_TEST.arff
datasets/FacesUCR/FacesUCR_TEST.ts
datasets/FacesUCR/FacesUCR_TEST.txt
datasets/FacesUCR/FacesUCR_TRAIN.arff
datasets/FacesUCR/FacesUCR_TRAIN.ts
datasets/FacesUCR/FacesUCR_TRAIN.txt
datasets/FreezerRegularTrain/FreezerRegularTrain.txt
datasets/FreezerRegularTrain/FreezerRegularTrain_TEST.arff
datasets/FreezerRegularTrain/FreezerRegularTrain_TEST.ts
datasets/FreezerRegularTrain/FreezerRegularTrain_TEST.txt
datasets/FreezerRegularTrain/FreezerRegularTrain_TRAIN.arff
datasets/FreezerRegularTrain/FreezerRegularTrain_TRAIN.ts
datasets/FreezerRegularTrain/FreezerRegularTrain_TRAIN.txt
datasets/FreezerRegularTrain/README.md
datasets/ItalyPowerDemand/ItalyPowerDemand.txt
datasets/ItalyPowerDemand/ItalyPowerDemand_TEST.arff
datasets/ItalyPowerDemand/ItalyPowerDemand_TEST.csv
datasets/ItalyPowerDemand/ItalyPowerDemand_TEST.ts
datasets/ItalyPowerDemand/ItalyPowerDemand_TEST.txt
datasets/ItalyPowerDemand/ItalyPowerDemand_TRAIN.arff
datasets/ItalyPowerDemand/ItalyPowerDemand_TRAIN.csv
datasets/ItalyPowerDemand/ItalyPowerDemand_TRAIN.ts
datasets/ItalyPowerDemand/ItalyPowerDemand_TRAIN.txt
datasets/MelbournePedestrian/MelbournePedestrian.txt
knn_Lbenhanced.egg-info/PKG-INFO
knn_Lbenhanced.egg-info/SOURCES.txt
knn_Lbenhanced.egg-info/dependency_links.txt
knn_Lbenhanced.egg-info/requires.txt
knn_Lbenhanced.egg-info/top_level.txt
