Metadata-Version: 1.2
Name: knn-Lbenhanced
Version: 1.2
Summary: K Nearest Neighbours using LbEnhanced distance measure
Home-page: https://github.com/moradisten/KNN-LB
Author: Moradisten
Author-email: moradabaz@gmail.com
License: UNKNOWN
Keywords: timeseries knn lowerbounds DTW lbEnhanced
Platform: UNKNOWN
Requires-Python: >=3.6
